odoo/addons/l10n_es_igic_reav/README.rst
odoo/addons/l10n_es_igic_reav/__init__.py
odoo/addons/l10n_es_igic_reav/__manifest__.py
odoo/addons/l10n_es_igic_reav/data/template/account.fiscal.position-es_full_canary.csv
odoo/addons/l10n_es_igic_reav/data/template/account.fiscal.position-es_pymes_canary.csv
odoo/addons/l10n_es_igic_reav/data/template/account.tax-es_full_canary.csv
odoo/addons/l10n_es_igic_reav/data/template/account.tax-es_pymes_canary.csv
odoo/addons/l10n_es_igic_reav/i18n/l10n_es_igic_reav.pot
odoo/addons/l10n_es_igic_reav/models/__init__.py
odoo/addons/l10n_es_igic_reav/models/account_chart_template.py
odoo/addons/l10n_es_igic_reav/readme/CONFIGURE.md
odoo/addons/l10n_es_igic_reav/readme/CONTRIBUTORS.md
odoo/addons/l10n_es_igic_reav/readme/DESCRIPTION.md
odoo/addons/l10n_es_igic_reav/readme/USAGE.md
odoo/addons/l10n_es_igic_reav/static/description/icon.png
odoo/addons/l10n_es_igic_reav/static/description/index.html
odoo/addons/l10n_es_igic_reav/tests/__init__.py
odoo/addons/l10n_es_igic_reav/tests/test_l10n_es_igic_reav.py
odoo_addon_l10n_es_igic_reav-17.0.1.0.3.dist-info/METADATA
odoo_addon_l10n_es_igic_reav-17.0.1.0.3.dist-info/WHEEL
odoo_addon_l10n_es_igic_reav-17.0.1.0.3.dist-info/top_level.txt
odoo_addon_l10n_es_igic_reav-17.0.1.0.3.dist-info/RECORD
